reward_scope/__init__.py
reward_scope/cli.py
reward_scope/py.typed
reward_scope/core/__init__.py
reward_scope/core/baseline.py
reward_scope/core/baselines.py
reward_scope/core/collector.py
reward_scope/core/decomposer.py
reward_scope/core/detectors.py
reward_scope/dashboard/__init__.py
reward_scope/dashboard/app.py
reward_scope/dashboard/templates/base.html
reward_scope/dashboard/templates/index.html
reward_scope/dashboard/templates/static/charts.js
reward_scope/dashboard/templates/static/styles.css
reward_scope/integrations/__init__.py
reward_scope/integrations/gymnasium.py
reward_scope/integrations/stable_baselines.py
reward_scope/utils/__init__.py
reward_scope/utils/export.py
reward_scope-0.2.2.dist-info/licenses/LICENSE
reward_scope-0.2.2.dist-info/METADATA
reward_scope-0.2.2.dist-info/WHEEL
reward_scope-0.2.2.dist-info/entry_points.txt
reward_scope-0.2.2.dist-info/top_level.txt
reward_scope-0.2.2.dist-info/RECORD
